{
  "id": "RAW_1989440354110898654",
  "title": "与 Gamma 创始人 Grant Lee 的访谈要点",
  "url": "https://x.com/lennysan/status/1989440354110898654",
  "date": "2025-11-14 21:08:37",
  "author": "Lenny Rachitsky",
  "siteName": "Lenny Rachitsky(@lennysan)",
  "content": null,
  "aiSummary": "Lenny Rachitsky 总结了与 Gamma 创始人 Grant Lee 的对话中的 8 个关键经验教训，涵盖产品体验、增长策略、招聘、用户测试和创始人思维。",
  "oneSentenceSummary": "Lenny Rachitsky 总结了与 Gamma 创始人 Grant Lee 的对话中的 8 个关键经验教训，涵盖产品体验、增长策略、招聘、用户测试和创始人思维。",
  "summary": "这条推文总结了与成功的 AI 初创公司 Gamma 的创始人 Grant Lee 访谈的 8 个关键要点。这些经验涵盖了产品和公司发展的各个方面：优先考虑卓越的最初 30 秒用户体验，专注于单一产品价值，延迟付费广告直到自然口碑增长强劲，利用微型网红，亲自指导早期创作者，缓慢而有选择的招聘，通过用户测试进行快速原型设计，以及选择创始人长期热衷的问题。这些见解为产品经理、创始人及创业团队提供了实用且可操作的建议，均来自于 Gamma 实现盈利和显著估值的实践。",
  "mainPoints": [],
  "keyQuotes": [],
  "tags": [
    "Startup Strategy",
    "Product Growth",
    "Word-of-Mouth",
    "User Testing",
    "Hiring"
  ],
  "topicTag": "product-business",
  "readTime": 13,
  "score": 92,
  "wordCount": 3093,
  "domain": "x.com",
  "category": "Artificial_Intelligence",
  "aiSubCategory": "PRODUCT",
  "mainDomain": "Artificial_Intelligence",
  "sourceId": "SOURCE_7a7b4c",
  "sourceName": "Lenny Rachitsky(@lennysan)",
  "resourceType": "TWITTER",
  "language": "en_US",
  "publishTimeStamp": 1763154517000,
  "publishDateStr": "2025-11-14",
  "publishDateTimeStr": "2025-11-14 21:08:37"
}
