{
  "id": "RAW_edb6a954",
  "title": "Go 闭包使用指南",
  "url": "https://www.freecodecamp.org/news/how-to-use-closures-in-go/",
  "date": "2025-10-27 20:35:29",
  "author": "Gabor Koos",
  "siteName": "freeCodeCamp.org",
  "content": "<html>\n <head></head>\n <body>\n  <p>If you've written code in JavaScript, Python, or Rust, you've probably heard the word <em>closure</em> before. The concept has subtle differences in each language, but the core idea is the same: a closure is a function that captures variables from its surrounding scope. This allows the function to \"remember\" the environment in which it was created, even when it's executed outside that environment, which has powerful implications for how we write and structure our code.</p>\n  <p>In this article, we'll explore how closures work in Go, a statically typed language known for its simplicity and efficiency. We'll look at how to create closures, how they capture variables, and some practical use cases.</p>\n  <h2 id=\"heading-what-well-cover\">What We'll Cover</h2>\n  <ul>\n   <li>\n    <p><a class=\"post-section-overview\" href=\"#heading-prerequisites\">Prerequisites</a></p>\n   </li>\n   <li>\n    <p><a class=\"post-section-overview\" href=\"#heading-what-closures-really-are-in-go\">What Closures Really Are in Go</a></p>\n    <ul>\n     <li>\n      <p><a class=\"post-section-overview\" href=\"#heading-how-go-makes-this-work\">How Go Makes This Work</a></p>\n     </li>\n     <li>\n      <p><a class=\"post-section-overview\" href=\"#heading-multiple-independent-closures\">Multiple Independent Closures</a></p>\n     </li>\n    </ul>\n   </li>\n   <li>\n    <p><a class=\"post-section-overview\" href=\"#heading-the-classic-loop-trap\">The Classic Loop Trap</a></p>\n   </li>\n   <li>\n    <p><a class=\"post-section-overview\" href=\"#heading-how-to-create-closures-in-go\">How to Create Closures in Go</a></p>\n    <ul>\n     <li>\n      <p><a class=\"post-section-overview\" href=\"#heading-returning-closures-from-functions\">Returning Closures From Functions</a></p>\n     </li>\n     <li>\n      <p><a class=\"post-section-overview\" href=\"#heading-named-inner-functions\">Named Inner Functions</a></p>\n     </li>\n     <li>\n      <p><a class=\"post-section-overview\" href=\"#heading-inline-closures-in-loops-or-goroutines\">Inline Closures in Loops or Goroutines</a></p>\n     </li>\n     <li>\n      <p><a class=\"post-section-overview\" href=\"#heading-closures-with-parameters\">Closures With Parameters</a></p>\n     </li>\n     <li>\n      <p><a class=\"post-section-overview\" href=\"#heading-capturing-multiple-variables\">Capturing Multiple Variables</a></p>\n     </li>\n     <li>\n      <p><a class=\"post-section-overview\" href=\"#heading-closures-in-structs\">Closures in Structs</a></p>\n     </li>\n     <li>\n      <p><a class=\"post-section-overview\" href=\"#heading-note-on-method-receivers\">Note on Method Receivers</a></p>\n     </li>\n     <li>\n      <p><a class=\"post-section-overview\" href=\"#heading-key-takeaways\">Key Takeaways</a></p>\n     </li>\n    </ul>\n   </li>\n   <li>\n    <p><a class=\"post-section-overview\" href=\"#heading-closures-and-concurrency\">Closures and Concurrency</a></p>\n    <ul>\n     <li>\n      <p><a class=\"post-section-overview\" href=\"#heading-independent-state-across-goroutines\">Independent State Across Goroutines</a></p>\n     </li>\n     <li>\n      <p><a class=\"post-section-overview\" href=\"#heading-capturing-shared-variables-safely\">Capturing Shared Variables Safely</a></p>\n     </li>\n    </ul>\n   </li>\n   <li>\n    <p><a class=\"post-section-overview\" href=\"#heading-practical-patterns-with-closures\">Practical Patterns with Closures</a></p>\n    <ul>\n     <li>\n      <p><a class=\"post-section-overview\" href=\"#heading-memoization-caching\">Memoization / Caching</a></p>\n     </li>\n     <li>\n      <p><a class=\"post-section-overview\" href=\"#heading-event-handlers-callbacks\">Event Handlers / Callbacks</a></p>\n     </li>\n     <li>\n      <p><a class=\"post-section-overview\" href=\"#heading-encapsulated-pipelines-producers\">Encapsulated Pipelines / Producers</a></p>\n     </li>\n     <li>\n      <p><a class=\"post-section-overview\" href=\"#heading-deferred-execution-with-captured-state\">Deferred Execution with Captured State</a></p>\n     </li>\n     <li>\n      <p><a class=\"post-section-overview\" href=\"#heading-how-to-implement-interfaces-dynamically\">How to Implement Interfaces Dynamically</a></p>\n     </li>\n     <li>\n      <p><a class=\"post-section-overview\" href=\"#heading-key-takeaways-1\">Key Takeaways</a></p>\n     </li>\n    </ul>\n   </li>\n   <li>\n    <p><a class=\"post-section-overview\" href=\"#heading-how-closures-affect-memory-and-performance\">How Closures Affect Memory and Performance</a></p>\n    <ul>\n     <li>\n      <p><a class=\"post-section-overview\" href=\"#heading-variables-may-live-longer-than-expected\">Variables May Live Longer Than Expected</a></p>\n     </li>\n     <li>\n      <p><a class=\"post-section-overview\" href=\"#heading-many-closures-can-add-overhead\">Many Closures Can Add Overhead</a></p>\n     </li>\n    </ul>\n   </li>\n   <li>\n    <p><a class=\"post-section-overview\" href=\"#heading-how-to-test-and-debug-closures\">How to Test and Debug Closures</a></p>\n    <ul>\n     <li>\n      <p><a class=\"post-section-overview\" href=\"#heading-isolate-the-closure\">Isolate the Closure</a></p>\n     </li>\n     <li>\n      <p><a class=\"post-section-overview\" href=\"#heading-check-captured-variables\">Check Captured Variables</a></p>\n     </li>\n     <li>\n      <p><a class=\"post-section-overview\" href=\"#heading-use-logging-or-debug-prints\">Use Logging or Debug Prints</a></p>\n     </li>\n     <li>\n      <p><a class=\"post-section-overview\" href=\"#heading-test-concurrency-carefully\">Test Concurrency Carefully</a></p>\n     </li>\n     <li>\n      <p><a class=\"post-section-overview\" href=\"#heading-key-takeaways-2\">Key Takeaways</a></p>\n     </li>\n    </ul>\n   </li>\n   <li>\n    <p><a class=\"post-section-overview\" href=\"#heading-best-practices-and-takeaways-for-using-closures-in-go\">Best Practices and Takeaways for Using Closures in Go</a></p>\n   </li>\n   <li>\n    <p><a class=\"post-section-overview\" href=\"#heading-conclusion\">Conclusion</a></p>\n   </li>\n  </ul>\n  <h2 id=\"heading-prerequisites\">Prerequisites</h2>\n  <p>To follow along with this article, you should have a basic understanding of Go programming, including functions and variable scope. If you're new to Go, consider checking out the <a target=\"_blank\" href=\"https://tour.golang.org/\">official Go tour</a> to get up to speed.</p>\n  <h2 id=\"heading-what-closures-really-are-in-go\">What Closures Really Are in Go</h2>\n  <p>At its simplest, a closure in Go is a function that <strong>references variables defined outside of it</strong>. That may sound abstract, so let's start with an example you can run right away:</p>\n  <pre><code class=\"lang-go\"><span class=\"hljs-keyword\">package</span> main\n\n<span class=\"hljs-keyword\">import</span> <span class=\"hljs-string\">\"fmt\"</span>\n\n<span class=\"hljs-function\"><span class=\"hljs-keyword\">func</span> <span class=\"hljs-title\">counter</span><span class=\"hljs-params\">()</span> <span class=\"hljs-title\">func</span><span class=\"hljs-params\">()</span> <span class=\"hljs-title\">int</span></span> {\n    n := <span class=\"hljs-number\">0</span>\n    <span class=\"hljs-keyword\">return</span> <span class=\"hljs-function\"><span class=\"hljs-keyword\">func</span><span class=\"hljs-params\">()</span> <span class=\"hljs-title\">int</span></span> {\n        n++\n        <span class=\"hljs-keyword\">return</span> n\n    }\n}\n\n<span class=\"hljs-function\"><span class=\"hljs-keyword\">func</span> <span class=\"hljs-title\">main</span><span class=\"hljs-params\">()</span></span> {\n    next := counter()\n    fmt.Println(next()) <span class=\"hljs-comment\">// 1</span>\n    fmt.Println(next()) <span class=\"hljs-comment\">// 2</span>\n    fmt.Println(next()) <span class=\"hljs-comment\">// 3</span>\n}\n</code></pre>\n  <p>When you call <code>counter()</code>, it returns another function, but that function <strong>keeps access to the variable</strong> <code>n</code> that lived inside counter.</p>\n  <p>Even though <code>counter()</code> has already finished running, <code>n</code> hasn't disappeared. Each time you call <code>next()</code>, it updates the same <code>n</code> that was created during the original <code>counter()</code> call.</p>\n  <p>This is the defining property of a closure:</p>\n  <blockquote>\n   <p>A closure \"closes over\" its environment, keeping the variables it needs alive for as long as the closure itself exists.</p>\n  </blockquote>\n  <h3 id=\"heading-how-go-makes-this-work\">How Go Makes This Work</h3>\n  <p>Normally, local variables in Go live on the <strong>stack</strong>, which is cleared when a function returns.</p>\n  <p>But if a nested function needs to keep using one of those variables, Go's compiler performs what's called <em>escape analysis</em>: it sees that the variable will outlive the function call, so it moves that variable to the <strong>heap</strong>, where it can stay alive as long as something references it - in this case, the closure.</p>\n  <p>You can actually ask the compiler to show you this process:</p>\n  <pre><code class=\"lang-bash\">go build -gcflags=<span class=\"hljs-string\">\"-m\"</span> main.go\n</code></pre>\n  <p>You might see output like:</p>\n  <pre><code class=\"lang-bash\">./main.go:6:6: moved to heap: n\n</code></pre>\n  <p>That tells you the variable <code>n</code> \"escaped\" the stack so the closure could use it safely later.</p>\n  <h3 id=\"heading-multiple-independent-closures\">Multiple Independent Closures</h3>\n  <p>Each call to a function that returns a closure creates a new, independent environment:</p>\n  <pre><code class=\"lang-go\">a := counter()\nb := counter()\nfmt.Println(a()) <span class=\"hljs-comment\">// 1</span>\nfmt.Println(a()) <span class=\"hljs-comment\">// 2</span>\nfmt.Println(b()) <span class=\"hljs-comment\">// 1</span>\n</code></pre>\n  <p>Here, <code>a</code> and <code>b</code> are two separate closures, each with its own <code>n</code>. Calling <code>a()</code> increments its own <code>n</code>, while calling <code>b()</code> starts from its own separate <code>n</code>.</p>\n  <h2 id=\"heading-the-classic-loop-trap\">The Classic Loop Trap</h2>\n  <p>One of the most common surprises for Go developers comes when closures are used inside a loop. Even experienced programmers often fall into this trap.</p>\n  <p>Consider this example:</p>\n  <pre><code class=\"lang-go\"><span class=\"hljs-keyword\">package</span> main\n\n<span class=\"hljs-keyword\">import</span> <span class=\"hljs-string\">\"fmt\"</span>\n\n<span class=\"hljs-function\"><span class=\"hljs-keyword\">func</span> <span class=\"hljs-title\">main</span><span class=\"hljs-params\">()</span></span> {\n    funcs := <span class=\"hljs-built_in\">make</span>([]<span class=\"hljs-function\"><span class=\"hljs-keyword\">func</span><span class=\"hljs-params\">()</span>, 0)</span>\n    <span class=\"hljs-keyword\">for</span> i := <span class=\"hljs-number\">0</span>; i &lt; <span class=\"hljs-number\">3</span>; i++ {\n        funcs = <span class=\"hljs-built_in\">append</span>(funcs, <span class=\"hljs-function\"><span class=\"hljs-keyword\">func</span><span class=\"hljs-params\">()</span></span> {\n            fmt.Println(i)\n        })\n    }\n    <span class=\"hljs-keyword\">for</span> _, f := <span class=\"hljs-keyword\">range</span> funcs {\n        f()\n    }\n}\n</code></pre>\n  <p>You might expect this to print <code>0</code>, <code>1</code>, and <code>2</code>, but it actually prints</p>\n  <pre><code class=\"lang-bash\">3\n3\n3\n</code></pre>\n  <p><strong>Why Does this Happen?</strong></p>\n  <p>Inside the loop, each function literal <strong>captures the variable</strong> <code>i</code> itself, not its value at that moment.</p>\n  <p>The loop reuses the same <code>i</code> variable for all iterations. By the time the loop finishes, <code>i</code> equals 3, and <strong>all the closures see this same</strong> <code>i</code> when they run later.</p>\n  <p><strong>How to Fix It</strong></p>\n  <p>There are two common idiomatic fixes:</p>\n  <ol>\n   <li>Shadow the loop variable:</li>\n  </ol>\n  <pre><code class=\"lang-go\"><span class=\"hljs-keyword\">for</span> i := <span class=\"hljs-number\">0</span>; i &lt; <span class=\"hljs-number\">3</span>; i++ {\n    i := i <span class=\"hljs-comment\">// new variable shadows the loop variable</span>\n    funcs = <span class=\"hljs-built_in\">append</span>(funcs, <span class=\"hljs-function\"><span class=\"hljs-keyword\">func</span><span class=\"hljs-params\">()</span></span> {\n        fmt.Println(i)\n    })\n}\n</code></pre>\n  <ol start=\"2\">\n   <li>Pass the variable as a parameter to an inner function:</li>\n  </ol>\n  <pre><code class=\"lang-go\"><span class=\"hljs-keyword\">for</span> i := <span class=\"hljs-number\">0</span>; i &lt; <span class=\"hljs-number\">3</span>; i++ {\n    funcs = <span class=\"hljs-built_in\">append</span>(funcs, <span class=\"hljs-function\"><span class=\"hljs-keyword\">func</span><span class=\"hljs-params\">(x <span class=\"hljs-keyword\">int</span>)</span> <span class=\"hljs-title\">func</span><span class=\"hljs-params\">()</span></span> {\n        <span class=\"hljs-keyword\">return</span> <span class=\"hljs-function\"><span class=\"hljs-keyword\">func</span><span class=\"hljs-params\">()</span></span> { fmt.Println(x) }\n    }(i))\n}\n</code></pre>\n  <p>Both approaches create a new variable for each iteration, so each closure captures its own independent value.</p>\n  <p>There are a few different ways to create closures in Go. Let's explore some common patterns.</p>\n  <h3 id=\"heading-returning-closures-from-functions\">Returning Closures From Functions</h3>\n  <p>The most common pattern is having a function return a closure that keeps its own state:</p>\n  <pre><code class=\"lang-go\"><span class=\"hljs-function\"><span class=\"hljs-keyword\">func</span> <span class=\"hljs-title\">makeCounter</span><span class=\"hljs-params\">()</span> <span class=\"hljs-title\">func</span><span class=\"hljs-params\">()</span> <span class=\"hljs-title\">int</span></span> {\n    n := <span class=\"hljs-number\">0</span>\n    <span class=\"hljs-keyword\">return</span> <span class=\"hljs-function\"><span class=\"hljs-keyword\">func</span><span class=\"hljs-params\">()</span> <span class=\"hljs-title\">int</span></span> {\n        n++\n        <span class=\"hljs-keyword\">return</span> n\n    }\n}\n\nc1 := makeCounter()\nfmt.Println(c1()) <span class=\"hljs-comment\">// 1</span>\nfmt.Println(c1()) <span class=\"hljs-comment\">// 2</span>\n</code></pre>\n  <p>Each call to <code>makeCounter</code> creates a new closure with its own <code>n</code>, as we saw earlier.</p>\n  <h3 id=\"heading-named-inner-functions\">Named Inner Functions</h3>\n  <p>You can also give a name to a function literal for readability or debugging:</p>\n  <pre><code class=\"lang-go\"><span class=\"hljs-function\"><span class=\"hljs-keyword\">func</span> <span class=\"hljs-title\">makeCounter</span><span class=\"hljs-params\">()</span> <span class=\"hljs-title\">func</span><span class=\"hljs-params\">()</span> <span class=\"hljs-title\">int</span></span> {\n    n := <span class=\"hljs-number\">0</span>\n    next := <span class=\"hljs-function\"><span class=\"hljs-keyword\">func</span> <span class=\"hljs-title\">incr</span><span class=\"hljs-params\">()</span> <span class=\"hljs-title\">int</span></span> {\n        n++\n        <span class=\"hljs-keyword\">return</span> n\n    }\n    <span class=\"hljs-keyword\">return</span> next\n}\n</code></pre>\n  <p>This works the same way but gives the inner function a name (<code>incr</code>), which can be helpful in stack traces. Other than that, it behaves just like an anonymous function.</p>\n  <h3 id=\"heading-inline-closures-in-loops-or-goroutines\">Inline Closures in Loops or Goroutines</h3>\n  <p>Closures are often defined inline, especially for loops or goroutines:</p>\n  <pre><code class=\"lang-go\"><span class=\"hljs-keyword\">for</span> i := <span class=\"hljs-number\">0</span>; i &lt; <span class=\"hljs-number\">3</span>; i++ {\n    <span class=\"hljs-keyword\">go</span> <span class=\"hljs-function\"><span class=\"hljs-keyword\">func</span><span class=\"hljs-params\">(x <span class=\"hljs-keyword\">int</span>)</span></span> {\n        fmt.Println(x)\n    }(i)\n}\n</code></pre>\n  <p>Here, we pass <code>i</code> as a parameter to the closure, ensuring each goroutine gets its own copy of the value, avoiding the loop variable trap.</p>\n  <h3 id=\"heading-closures-with-parameters\">Closures With Parameters</h3>\n  <p>Closures can accept their own arguments:</p>\n  <pre><code class=\"lang-go\"><span class=\"hljs-function\"><span class=\"hljs-keyword\">func</span> <span class=\"hljs-title\">adder</span><span class=\"hljs-params\">(base <span class=\"hljs-keyword\">int</span>)</span> <span class=\"hljs-title\">func</span><span class=\"hljs-params\">(<span class=\"hljs-keyword\">int</span>)</span> <span class=\"hljs-title\">int</span></span> {\n    <span class=\"hljs-keyword\">return</span> <span class=\"hljs-function\"><span class=\"hljs-keyword\">func</span><span class=\"hljs-params\">(x <span class=\"hljs-keyword\">int</span>)</span> <span class=\"hljs-title\">int</span></span> {\n        <span class=\"hljs-keyword\">return</span> base + x\n    }\n}\n\nadd5 := adder(<span class=\"hljs-number\">5</span>)\nfmt.Println(add5(<span class=\"hljs-number\">10</span>)) <span class=\"hljs-comment\">// 15</span>\n</code></pre>\n  <p>Here, <code>adder</code> returns a closure that adds a fixed <code>base</code> value to whatever argument it receives.</p>\n  <h3 id=\"heading-capturing-multiple-variables\">Capturing Multiple Variables</h3>\n  <p>Closures can capture multiple outer variables:</p>\n  <pre><code class=\"lang-go\"><span class=\"hljs-function\"><span class=\"hljs-keyword\">func</span> <span class=\"hljs-title\">multiplier</span><span class=\"hljs-params\">(factor <span class=\"hljs-keyword\">int</span>)</span> <span class=\"hljs-title\">func</span><span class=\"hljs-params\">(<span class=\"hljs-keyword\">int</span>)</span> <span class=\"hljs-title\">int</span></span> {\n    offset := <span class=\"hljs-number\">2</span>\n    <span class=\"hljs-keyword\">return</span> <span class=\"hljs-function\"><span class=\"hljs-keyword\">func</span><span class=\"hljs-params\">(x <span class=\"hljs-keyword\">int</span>)</span> <span class=\"hljs-title\">int</span></span> {\n        <span class=\"hljs-keyword\">return</span> x*factor + offset\n    }\n}\n\nm := multiplier(<span class=\"hljs-number\">3</span>)\nfmt.Println(m(<span class=\"hljs-number\">4</span>)) <span class=\"hljs-comment\">// 14</span>\n</code></pre>\n  <p>In this example, the closure captures both <code>factor</code> and <code>offset</code> from its surrounding scope - <code>factor</code> is a parameter, while <code>offset</code> is a local variable.</p>\n  <h3 id=\"heading-closures-in-structs\">Closures in Structs</h3>\n  <p>Closures can also be stored in structs, just like any other function value. This is a useful pattern when you want objects with dynamic or stateful behavior.</p>\n  <pre><code class=\"lang-go\"><span class=\"hljs-keyword\">type</span> Counter <span class=\"hljs-keyword\">struct</span> {\n    Next <span class=\"hljs-function\"><span class=\"hljs-keyword\">func</span><span class=\"hljs-params\">()</span> <span class=\"hljs-title\">int</span></span>\n}\n\n<span class=\"hljs-function\"><span class=\"hljs-keyword\">func</span> <span class=\"hljs-title\">NewCounter</span><span class=\"hljs-params\">()</span> <span class=\"hljs-title\">Counter</span></span> {\n    n := <span class=\"hljs-number\">0</span>\n    <span class=\"hljs-keyword\">return</span> Counter{\n        Next: <span class=\"hljs-function\"><span class=\"hljs-keyword\">func</span><span class=\"hljs-params\">()</span> <span class=\"hljs-title\">int</span></span> {\n            n++\n            <span class=\"hljs-keyword\">return</span> n\n        },\n    }\n}\n\n<span class=\"hljs-function\"><span class=\"hljs-keyword\">func</span> <span class=\"hljs-title\">main</span><span class=\"hljs-params\">()</span></span> {\n    c := NewCounter()\n    fmt.Println(c.Next()) <span class=\"hljs-comment\">// 1</span>\n    fmt.Println(c.Next()) <span class=\"hljs-comment\">// 2</span>\n}\n</code></pre>\n  <p>Here, the <code>Next</code> field holds a closure that captures the variable <code>n</code>. Each instance of <code>Counter</code> has its own independent state, without needing a separate type or mutex.</p>\n  <p>This pattern shows how closures can act as lightweight objects: bundling behavior and state together.</p>\n  <h3 id=\"heading-note-on-method-receivers\">Note on Method Receivers</h3>\n  <p>Closures in Go don't implicitly capture the method receiver like some languages do. If you want a closure to use the receiver inside a method, you typically assign it to a local variable:</p>\n  <pre><code class=\"lang-go\"><span class=\"hljs-keyword\">type</span> Counter <span class=\"hljs-keyword\">struct</span> {\n    n <span class=\"hljs-keyword\">int</span>\n}\n\n<span class=\"hljs-function\"><span class=\"hljs-keyword\">func</span> <span class=\"hljs-params\">(c *Counter)</span> <span class=\"hljs-title\">MakeIncrementer</span><span class=\"hljs-params\">()</span> <span class=\"hljs-title\">func</span><span class=\"hljs-params\">()</span> <span class=\"hljs-title\">int</span></span> {\n    r := c <span class=\"hljs-comment\">// capture receiver explicitly</span>\n    <span class=\"hljs-keyword\">return</span> <span class=\"hljs-function\"><span class=\"hljs-keyword\">func</span><span class=\"hljs-params\">()</span> <span class=\"hljs-title\">int</span></span> {\n        r.n++\n        <span class=\"hljs-keyword\">return</span> r.n\n    }\n}\n</code></pre>\n  <p>This ensures the closure references the intended receiver rather than introducing unexpected behavior.</p>\n  <p>Unlike JavaScript or Python, Go closures capture lexical variables, not the implicit <code>this</code> or <code>self</code>.</p>\n  <h3 id=\"heading-key-takeaways\">Key Takeaways</h3>\n  <ul>\n   <li>\n    <p>Closures can be returned from functions, named, inlined, or even stored in structs.</p>\n   </li>\n   <li>\n    <p>They capture outer variables, not copies of their values.</p>\n   </li>\n   <li>\n    <p>Used this way, closures can replace small types or interfaces for lightweight encapsulation.</p>\n   </li>\n  </ul>\n  <h2 id=\"heading-closures-and-concurrency\">Closures and Concurrency</h2>\n  <p>Closures are powerful in Go, but when you combine them with concurrency, their captured variables can act in unexpected ways if you're not careful.</p>\n  <h3 id=\"heading-independent-state-across-goroutines\">Independent State Across Goroutines</h3>\n  <p>Each closure keeps its own captured variables alive, even when used in concurrent goroutines:</p>\n  <pre><code class=\"lang-go\"><span class=\"hljs-function\"><span class=\"hljs-keyword\">func</span> <span class=\"hljs-title\">makeWorker</span><span class=\"hljs-params\">(start <span class=\"hljs-keyword\">int</span>)</span> <span class=\"hljs-title\">func</span><span class=\"hljs-params\">()</span> <span class=\"hljs-title\">int</span></span> {\n    counter := start\n    <span class=\"hljs-keyword\">return</span> <span class=\"hljs-function\"><span class=\"hljs-keyword\">func</span><span class=\"hljs-params\">()</span> <span class=\"hljs-title\">int</span></span> {\n        counter++\n        <span class=\"hljs-keyword\">return</span> counter\n    }\n}\n\n<span class=\"hljs-function\"><span class=\"hljs-keyword\">func</span> <span class=\"hljs-title\">main</span><span class=\"hljs-params\">()</span></span> {\n    worker1 := makeWorker(<span class=\"hljs-number\">0</span>)\n    worker2 := makeWorker(<span class=\"hljs-number\">100</span>)\n\n    <span class=\"hljs-keyword\">go</span> <span class=\"hljs-function\"><span class=\"hljs-keyword\">func</span><span class=\"hljs-params\">()</span></span> { fmt.Println(worker1()) }() <span class=\"hljs-comment\">// prints 1</span>\n    <span class=\"hljs-keyword\">go</span> <span class=\"hljs-function\"><span class=\"hljs-keyword\">func</span><span class=\"hljs-params\">()</span></span> { fmt.Println(worker2()) }() <span class=\"hljs-comment\">// prints 101</span>\n}\n</code></pre>\n  <p>Here, <code>worker1</code> and <code>worker2</code> have independent <code>counter</code> variables, so they don't interfere with each other. Each closure maintains independent state, even in separate goroutines.</p>\n  <h3 id=\"heading-capturing-shared-variables-safely\">Capturing Shared Variables Safely</h3>\n  <p>When multiple closures share a variable, you must coordinate access. For example:</p>\n  <pre><code class=\"lang-go\">counter := <span class=\"hljs-number\">0</span>\nch := <span class=\"hljs-built_in\">make</span>(<span class=\"hljs-keyword\">chan</span> <span class=\"hljs-keyword\">int</span>)\n\n<span class=\"hljs-keyword\">for</span> i := <span class=\"hljs-number\">0</span>; i &lt; <span class=\"hljs-number\">3</span>; i++ {\n    <span class=\"hljs-keyword\">go</span> <span class=\"hljs-function\"><span class=\"hljs-keyword\">func</span><span class=\"hljs-params\">()</span></span> {\n        <span class=\"hljs-comment\">// increments a shared variable</span>\n        ch &lt;- <span class=\"hljs-number\">1</span>\n    }()\n}\n\n<span class=\"hljs-comment\">// aggregate safely</span>\n<span class=\"hljs-keyword\">for</span> i := <span class=\"hljs-number\">0</span>; i &lt; <span class=\"hljs-number\">3</span>; i++ {\n    counter += &lt;-ch\n}\nfmt.Println(counter) <span class=\"hljs-comment\">// 3</span>\n</code></pre>\n  <p>The closure captures the outer variable <code>ch</code> (a channel), which is safe because channels serialize access. Using a buffered channel here wouldn't change the behavior of the closure: it still captures its own <code>n</code> and sends the values to the channel independently.</p>\n  <p>Closures themselves <strong>don't synchronize shared state, you still need channels or mutexes</strong>.</p>\n  <h2 id=\"heading-practical-patterns-with-closures\">Practical Patterns with Closures</h2>\n  <p>Closures in Go aren't just a language curiosity, they're a powerful tool for writing stateful, reusable, and flexible code. Here are a few practical patterns that go beyond the basics.</p>\n  <h3 id=\"heading-memoization-caching\">Memoization / Caching</h3>\n  <p>Closures can capture an internal map or cache to store results of expensive computations:</p>\n  <pre><code class=\"lang-go\"><span class=\"hljs-function\"><span class=\"hljs-keyword\">func</span> <span class=\"hljs-title\">memoize</span><span class=\"hljs-params\">(f <span class=\"hljs-keyword\">func</span>(<span class=\"hljs-keyword\">int</span>)</span> <span class=\"hljs-title\">int</span>) <span class=\"hljs-title\">func</span><span class=\"hljs-params\">(<span class=\"hljs-keyword\">int</span>)</span> <span class=\"hljs-title\">int</span></span> {\n    cache := <span class=\"hljs-keyword\">map</span>[<span class=\"hljs-keyword\">int</span>]<span class=\"hljs-keyword\">int</span>{}\n    <span class=\"hljs-keyword\">return</span> <span class=\"hljs-function\"><span class=\"hljs-keyword\">func</span><span class=\"hljs-params\">(x <span class=\"hljs-keyword\">int</span>)</span> <span class=\"hljs-title\">int</span></span> {\n        <span class=\"hljs-keyword\">if</span> val, ok := cache[x]; ok {\n            <span class=\"hljs-keyword\">return</span> val\n        }\n        result := f(x)\n        cache[x] = result\n        <span class=\"hljs-keyword\">return</span> result\n    }\n}\n\n<span class=\"hljs-function\"><span class=\"hljs-keyword\">func</span> <span class=\"hljs-title\">main</span><span class=\"hljs-params\">()</span></span> {\n    fib := memoize(<span class=\"hljs-function\"><span class=\"hljs-keyword\">func</span><span class=\"hljs-params\">(n <span class=\"hljs-keyword\">int</span>)</span> <span class=\"hljs-title\">int</span></span> {\n        <span class=\"hljs-keyword\">if</span> n &lt;= <span class=\"hljs-number\">1</span> {\n            <span class=\"hljs-keyword\">return</span> n\n        }\n        <span class=\"hljs-keyword\">return</span> fib(n<span class=\"hljs-number\">-1</span>) + fib(n<span class=\"hljs-number\">-2</span>)\n    })\n    fmt.Println(fib(<span class=\"hljs-number\">10</span>)) <span class=\"hljs-comment\">// 55</span>\n}\n</code></pre>\n  <p>Here, the <code>memoize</code> function returns a closure that caches results of the Fibonacci function, avoiding redundant calculations.</p>\n  <h3 id=\"heading-event-handlers-callbacks\">Event Handlers / Callbacks</h3>\n  <p>Closures are perfect for defining event handlers or callbacks that need to maintain state:</p>\n  <pre><code class=\"lang-go\"><span class=\"hljs-keyword\">type</span> Button <span class=\"hljs-keyword\">struct</span> {\n    onClick <span class=\"hljs-function\"><span class=\"hljs-keyword\">func</span><span class=\"hljs-params\">()</span></span>\n}\n\n<span class=\"hljs-function\"><span class=\"hljs-keyword\">func</span> <span class=\"hljs-params\">(b *Button)</span> <span class=\"hljs-title\">Click</span><span class=\"hljs-params\">()</span></span> {\n    <span class=\"hljs-keyword\">if</span> b.onClick != <span class=\"hljs-literal\">nil</span> {\n        b.onClick()\n    }\n}\n\n<span class=\"hljs-function\"><span class=\"hljs-keyword\">func</span> <span class=\"hljs-title\">main</span><span class=\"hljs-params\">()</span></span> {\n    count := <span class=\"hljs-number\">0</span>\n    button := Button{\n        onClick: <span class=\"hljs-function\"><span class=\"hljs-keyword\">func</span><span class=\"hljs-params\">()</span></span> {\n            count++\n            fmt.Println(<span class=\"hljs-string\">\"Button clicked\"</span>, count, <span class=\"hljs-string\">\"times\"</span>)\n        },\n    }\n\n    button.Click() <span class=\"hljs-comment\">// Button clicked 1 times</span>\n    button.Click() <span class=\"hljs-comment\">// Button clicked 2 times</span>\n}\n</code></pre>\n  <p>In this example, the closure captures the <code>count</code> variable, allowing the button to keep track of how many times it has been clicked.</p>\n  <h3 id=\"heading-encapsulated-pipelines-producers\">Encapsulated Pipelines / Producers</h3>\n  <p>Closures can wrap stateful logic for channels and pipelines:</p>\n  <pre><code class=\"lang-go\"><span class=\"hljs-function\"><span class=\"hljs-keyword\">func</span> <span class=\"hljs-title\">producer</span><span class=\"hljs-params\">(start <span class=\"hljs-keyword\">int</span>)</span> <span class=\"hljs-title\">func</span><span class=\"hljs-params\">(<span class=\"hljs-keyword\">chan</span> <span class=\"hljs-keyword\">int</span>)</span></span> {\n    n := start\n    <span class=\"hljs-keyword\">return</span> <span class=\"hljs-function\"><span class=\"hljs-keyword\">func</span><span class=\"hljs-params\">(ch <span class=\"hljs-keyword\">chan</span> <span class=\"hljs-keyword\">int</span>)</span></span> {\n        <span class=\"hljs-keyword\">for</span> i := <span class=\"hljs-number\">0</span>; i &lt; <span class=\"hljs-number\">3</span>; i++ {\n            ch &lt;- n\n            n++\n        }\n    }\n}\n\n<span class=\"hljs-function\"><span class=\"hljs-keyword\">func</span> <span class=\"hljs-title\">main</span><span class=\"hljs-params\">()</span></span> {\n    ch := <span class=\"hljs-built_in\">make</span>(<span class=\"hljs-keyword\">chan</span> <span class=\"hljs-keyword\">int</span>, <span class=\"hljs-number\">3</span>)\n    <span class=\"hljs-keyword\">go</span> producer(<span class=\"hljs-number\">5</span>)(ch)\n    <span class=\"hljs-keyword\">for</span> i := <span class=\"hljs-number\">0</span>; i &lt; <span class=\"hljs-number\">3</span>; i++ {\n        fmt.Println(&lt;-ch) <span class=\"hljs-comment\">// 5, 6, 7</span>\n    }\n}\n</code></pre>\n  <p>Here, the <code>producer</code> function returns a closure that sends a sequence of numbers to a channel, maintaining its own state with <code>n</code>.</p>\n  <h3 id=\"heading-deferred-execution-with-captured-state\">Deferred Execution with Captured State</h3>\n  <p>Using a closure with <code>defer</code> lets you capture variables at the moment the defer statement is executed, which is especially useful in loops or resource cleanup:</p>\n  <pre><code class=\"lang-go\"><span class=\"hljs-function\"><span class=\"hljs-keyword\">func</span> <span class=\"hljs-title\">main</span><span class=\"hljs-params\">()</span></span> {\n    <span class=\"hljs-keyword\">for</span> i := <span class=\"hljs-number\">0</span>; i &lt; <span class=\"hljs-number\">3</span>; i++ {\n        <span class=\"hljs-keyword\">defer</span> <span class=\"hljs-function\"><span class=\"hljs-keyword\">func</span><span class=\"hljs-params\">(x <span class=\"hljs-keyword\">int</span>)</span></span> {\n            fmt.Println(x)\n        }(i) <span class=\"hljs-comment\">// capture current i</span>\n    }\n}\n</code></pre>\n  <p>Output:</p>\n  <pre><code class=\"lang-bash\">2\n1\n0\n</code></pre>\n  <p>Here, each deferred closure captures the value of <code>i</code> at the time of the <code>defer</code> statement, so they print in reverse order when the function exits.</p>\n  <h3 id=\"heading-how-to-implement-interfaces-dynamically\">How to Implement Interfaces Dynamically</h3>\n  <p>Closures can also be used to implement interfaces without defining a full struct type. For example, a simple function can satisfy a single-method interface:</p>\n  <pre><code class=\"lang-go\"><span class=\"hljs-keyword\">type</span> Greeter <span class=\"hljs-keyword\">interface</span> {\n    Greet() <span class=\"hljs-keyword\">string</span>\n}\n\n<span class=\"hljs-function\"><span class=\"hljs-keyword\">func</span> <span class=\"hljs-title\">MakeGreeter</span><span class=\"hljs-params\">(name <span class=\"hljs-keyword\">string</span>)</span> <span class=\"hljs-title\">Greeter</span></span> {\n    <span class=\"hljs-keyword\">return</span> <span class=\"hljs-keyword\">struct</span>{ Greeter }{\n        Greeter: <span class=\"hljs-function\"><span class=\"hljs-keyword\">func</span><span class=\"hljs-params\">()</span> <span class=\"hljs-title\">string</span></span> { <span class=\"hljs-keyword\">return</span> <span class=\"hljs-string\">\"Hello, \"</span> + name },\n    }\n}\n\n<span class=\"hljs-function\"><span class=\"hljs-keyword\">func</span> <span class=\"hljs-title\">main</span><span class=\"hljs-params\">()</span></span> {\n    g := MakeGreeter(<span class=\"hljs-string\">\"Alice\"</span>)\n    fmt.Println(g.Greet()) <span class=\"hljs-comment\">// Hello, Alice</span>\n}\n</code></pre>\n  <p>Here, the closure captures <code>name</code>, allowing the returned object to implement the <code>Greet</code> method dynamically.</p>\n  <h3 id=\"heading-key-takeaways-1\">Key Takeaways</h3>\n  <ul>\n   <li>\n    <p>Closures allow memoization and caching without extra structs.</p>\n   </li>\n   <li>\n    <p>Storing closures in structs provides customizable behavior for objects.</p>\n   </li>\n   <li>\n    <p>Closures can encapsulate stateful concurrent pipelines, keeping logic localized and safe.</p>\n   </li>\n   <li>\n    <p>Closures with <code>defer</code> capture variables at the time of deferment, useful for cleanup or logging.</p>\n   </li>\n   <li>\n    <p>They enable dynamic interface implementations without boilerplate types.</p>\n   </li>\n  </ul>\n  <h2 id=\"heading-how-closures-affect-memory-and-performance\">How Closures Affect Memory and Performance</h2>\n  <p>Closures are powerful, but capturing variables from outer scopes has memory and performance implications.</p>\n  <h3 id=\"heading-variables-may-live-longer-than-expected\">Variables May Live Longer Than Expected</h3>\n  <p>Because closures keep references to captured variables (and move them to the heap if necessary, as we saw earlier), these variables live as long as the closure itself, which can increase memory usage:</p>\n  <pre><code class=\"lang-go\"><span class=\"hljs-function\"><span class=\"hljs-keyword\">func</span> <span class=\"hljs-title\">main</span><span class=\"hljs-params\">()</span></span> {\n    bigData := <span class=\"hljs-built_in\">make</span>([]<span class=\"hljs-keyword\">byte</span>, <span class=\"hljs-number\">10</span>_000_000) <span class=\"hljs-comment\">// 10MB</span>\n    f := <span class=\"hljs-function\"><span class=\"hljs-keyword\">func</span><span class=\"hljs-params\">()</span> <span class=\"hljs-title\">int</span></span> { <span class=\"hljs-keyword\">return</span> <span class=\"hljs-built_in\">len</span>(bigData) }\n    _ = f\n}\n</code></pre>\n  <p>In this example, <code>bigData</code> remains in memory as long as the closure <code>f</code> exists, even if <code>bigData</code> is no longer needed elsewhere.</p>\n  <h3 id=\"heading-many-closures-can-add-overhead\">Many Closures Can Add Overhead</h3>\n  <p>Each closure carries a small environment for its captured variables. Creating thousands of closures is usually fine, but in high-performance or memory-sensitive code, this can add measurable overhead.</p>\n  <ul>\n   <li>\n    <p>Captured variables may be heap-allocated.</p>\n   </li>\n   <li>\n    <p>Each closure has a small hidden struct for its environment.</p>\n   </li>\n  </ul>\n  <p>Alternatives include <strong>structs</strong> or <strong>plain functions</strong> when you need maximum efficiency.</p>\n  <h2 id=\"heading-how-to-test-and-debug-closures\">How to Test and Debug Closures</h2>\n  <p>Closures can sometimes behave in unexpected ways when capturing variables or working with concurrency. Here are some tips to test and debug them effectively.</p>\n  <h3 id=\"heading-isolate-the-closure\">Isolate the Closure</h3>\n  <p>Test the closure independently of its outer function to verify its behavior:</p>\n  <pre><code class=\"lang-go\"><span class=\"hljs-function\"><span class=\"hljs-keyword\">func</span> <span class=\"hljs-title\">TestCounter</span><span class=\"hljs-params\">(t *testing.T)</span></span> {\n    counter := makeCounter()\n    <span class=\"hljs-keyword\">if</span> counter() != <span class=\"hljs-number\">1</span> {\n        t.Error(<span class=\"hljs-string\">\"expected 1\"</span>)\n    }\n    <span class=\"hljs-keyword\">if</span> counter() != <span class=\"hljs-number\">2</span> {\n        t.Error(<span class=\"hljs-string\">\"expected 2\"</span>)\n    }\n}\n</code></pre>\n  <p>This ensures the closure maintains state correctly.</p>\n  <h3 id=\"heading-check-captured-variables\">Check Captured Variables</h3>\n  <p>Remember: closures capture variables by reference, not value. Be mindful of loop variables or shared state:</p>\n  <pre><code class=\"lang-go\"><span class=\"hljs-keyword\">for</span> i := <span class=\"hljs-number\">0</span>; i &lt; <span class=\"hljs-number\">3</span>; i++ {\n    i := i <span class=\"hljs-comment\">// shadow loop variable</span>\n    t.Run(fmt.Sprintf(<span class=\"hljs-string\">\"i=%d\"</span>, i), <span class=\"hljs-function\"><span class=\"hljs-keyword\">func</span><span class=\"hljs-params\">(t *testing.T)</span></span> {\n        <span class=\"hljs-keyword\">if</span> i != i { <span class=\"hljs-comment\">// simplified check</span>\n            t.Fail()\n        }\n    })\n}\n</code></pre>\n  <p>This helps avoid the loop trap in tests.</p>\n  <h3 id=\"heading-use-logging-or-debug-prints\">Use Logging or Debug Prints</h3>\n  <p>Printing internal closure state is often the fastest way to debug subtle behavior:</p>\n  <pre><code class=\"lang-go\">adder := <span class=\"hljs-function\"><span class=\"hljs-keyword\">func</span><span class=\"hljs-params\">(base <span class=\"hljs-keyword\">int</span>)</span> <span class=\"hljs-title\">func</span><span class=\"hljs-params\">(<span class=\"hljs-keyword\">int</span>)</span> <span class=\"hljs-title\">int</span></span> {\n    <span class=\"hljs-keyword\">return</span> <span class=\"hljs-function\"><span class=\"hljs-keyword\">func</span><span class=\"hljs-params\">(x <span class=\"hljs-keyword\">int</span>)</span> <span class=\"hljs-title\">int</span></span> {\n        fmt.Printf(<span class=\"hljs-string\">\"base=%d, x=%d\\n\"</span>, base, x)\n        <span class=\"hljs-keyword\">return</span> base + x\n    }\n}\nresult := adder(<span class=\"hljs-number\">5</span>)(<span class=\"hljs-number\">10</span>) <span class=\"hljs-comment\">// logs: base=5, x=10</span>\n</code></pre>\n  <h3 id=\"heading-test-concurrency-carefully\">Test Concurrency Carefully</h3>\n  <p>When closures are used in goroutines, race conditions can creep in. Use the Go race detector:</p>\n  <pre><code class=\"lang-bash\">go <span class=\"hljs-built_in\">test</span> -race ./...\n</code></pre>\n  <p>This flags any shared variable access that isn’t properly synchronized.</p>\n  <h3 id=\"heading-key-takeaways-2\">Key Takeaways</h3>\n  <ul>\n   <li>\n    <p>Test closures independently to ensure captured state behaves as expected.</p>\n   </li>\n   <li>\n    <p>Be cautious with loop variables and shared state.</p>\n   </li>\n   <li>\n    <p>Use logging and the race detector to debug concurrency issues.</p>\n   </li>\n  </ul>\n  <h2 id=\"heading-best-practices-and-takeaways-for-using-closures-in-go\">Best Practices and Takeaways for Using Closures in Go</h2>\n  <p>Closures are a versatile feature in Go, but like any tool, they work best when used thoughtfully. Here are some practical guidelines:</p>\n  <ul>\n   <li>\n    <p><strong>Encapsulate state cleanly</strong>: Use closures to maintain private state without introducing extra structs or types. Counters, memoization caches, and small factories are common patterns.</p>\n   </li>\n   <li>\n    <p><strong>Be careful in loops</strong>: Always capture loop variables correctly to avoid the classic loop trap. Shadowing the variable or passing it as a parameter to the closure are idiomatic solutions.</p>\n   </li>\n   <li>\n    <p><strong>Handle concurrency explicitly</strong>: Closures can safely maintain independent state in goroutines, but they do not synchronize shared state automatically. When multiple closures share variables, coordinate access with channels or mutexes.</p>\n   </li>\n   <li>\n    <p><strong>Mind memory usage</strong>: Captured variables may escape to the heap, so long-lived closures can retain more memory than expected. Avoid capturing large objects unless necessary.</p>\n   </li>\n   <li>\n    <p><strong>Leverage closures in structs</strong>: Storing closures in struct fields allows objects to have dynamic or customizable behavior without extra boilerplate, making your code more flexible.</p>\n   </li>\n  </ul>\n  <h2 id=\"heading-conclusion\">Conclusion</h2>\n  <p>Closures in Go allow functions to carry state, encapsulate behavior, and interact safely with concurrency patterns, all while keeping your code clean and expressive. By understanding how closures capture variables, how they behave in loops and goroutines, and their memory implications, you can use them confidently to write more idiomatic and maintainable Go code.</p>\n </body>\n</html>",
  "aiSummary": "Go 闭包的全面指南，涵盖机制、陷阱、应用、并发及最佳实践。",
  "oneSentenceSummary": "Go 闭包的全面指南，涵盖机制、陷阱、应用、并发及最佳实践。",
  "summary": "本文深入探讨 Go 中的闭包，这是用于编写具备状态且灵活代码的关键概念。首先，它将闭包定义为从其周围作用域捕获变量的函数，解释了 Go 的逃逸分析如何将这些变量移动到堆上，以确保它们的持久性。重点介绍了“经典循环陷阱”这一常见问题，即闭包捕获变量引用而非值，并提供了两种解决方案。然后，文章演示了创建闭包的各种方法，包括从函数返回闭包、命名内部函数、在循环/Go 程中内联使用以及将闭包存储在结构体中。重点介绍了实际模式，如备忘录模式、事件处理程序、封装管道、延迟执行和动态接口实现。讨论了并发场景下的注意事项，强调了在访问共享变量时进行显式同步的必要性。总结了内存/性能考量、调试技巧以及 Go 闭包的最佳实践。",
  "mainPoints": [
    {
      "point": "Go 闭包从其外部作用域捕获变量，Go 的逃逸分析管理它们在堆上的内存生命周期。",
      "explanation": "Go 中的闭包会记住创建时所在的作用域环境。编译器的逃逸分析确保闭包所需的变量从栈移动到堆，允许它们在父函数执行完毕后仍然存在。"
    },
    {
      "point": "“经典循环陷阱”是一个常见的陷阱，循环中的闭包捕获的是变量引用，而不是它们的值。",
      "explanation": "当闭包在循环中定义时，它们捕获的是循环变量本身。当闭包执行时，循环变量保存的是它的最终值，导致出现意想不到的行为。解决方案包括遮蔽变量或将其作为参数传递。"
    },
    {
      "point": "闭包为有状态、可重用和灵活的 Go 代码提供了多种实用的模式。",
      "explanation": "它们可以用于备忘录/缓存，创建有状态的事件处理程序/回调，封装管道，使用捕获的状态实现延迟执行，以及动态实现接口而无需样板结构体。"
    },
    {
      "point": "虽然闭包在 Go 程中保持独立状态，但共享变量需要显式同步。",
      "explanation": "每个闭包维护其自身捕获的变量，这对于并发使用是安全的。但是，当多个闭包与共享变量交互时，需要使用通道或互斥锁来防止竞态条件并确保数据完整性。"
    },
    {
      "point": "理解内存影响和有效的调试对于健壮的闭包使用至关重要。",
      "explanation": "捕获的变量可能在堆上存活更长时间，从而增加内存使用量。调试包括隔离闭包、检查捕获的变量、使用日志输出以及利用 Go 的竞态检测器来解决并发问题。"
    }
  ],
  "keyQuotes": [
    "闭包是从其周围作用域捕获变量的函数。",
    "闭包“捕获”其环境，只要闭包存在，就保持所需变量的存活。",
    "在循环内部，每个函数文字**捕获变量** `i` 本身，而不是那一刻它的值。",
    "闭包本身**不同步共享状态，你仍然需要通道或互斥锁**。",
    "使用闭包来维护私有状态，而无需引入额外的结构体或类型。"
  ],
  "tags": [
    "Go Programming",
    "闭包",
    "并发",
    "软件工程",
    "设计模式"
  ],
  "topicTag": "other",
  "readTime": 12,
  "score": 88,
  "wordCount": 2800,
  "domain": "freecodecamp.org",
  "category": "Programming_Technology",
  "aiSubCategory": "NEWS",
  "mainDomain": "Programming_Technology",
  "sourceId": "SOURCE_074370",
  "sourceName": "freeCodeCamp.org",
  "resourceType": "ARTICLE",
  "language": "en_US",
  "publishTimeStamp": 1761597329000,
  "publishDateStr": "2025-10-27",
  "publishDateTimeStr": "2025-10-27 20:35:29"
}
